lenmay/__init__.py
lenmay/main.py
lenmay/templates/test.sh.j2
lenmay/templates/init/jobber.sh.j2
lenmay/templates/init/linux.sh.j2
lenmay/templates/init/main.sh.j2
lenmay/templates/init/mysql.sh.j2
lenmay/templates/init/nginx.sh.j2
lenmay/templates/init/nodejs.sh.j2
lenmay/templates/init/php.sh.j2
lenmay/templates/init/redis.sh.j2
lenmay/templates/init/security.sh.j2
lenmay/templates/init/supervisor.sh.j2
lenmay/templates/web/create_site.sh.j2
lenmay/templates/web/create_user.sh.j2
lenmay-0.2.3.dist-info/LICENSE.txt
lenmay-0.2.3.dist-info/METADATA
lenmay-0.2.3.dist-info/WHEEL
lenmay-0.2.3.dist-info/entry_points.txt
lenmay-0.2.3.dist-info/top_level.txt
lenmay-0.2.3.dist-info/RECORD
