Metadata-Version: 2.1
Name: lenmay
Version: 0.2.3
Summary: CLI tool to len may!
Home-page: https://github.com/khanhicetea/lenmay
Author: KhanhIceTea
Author-email: khanhicetea@gmail.com
License: UNKNOWN
Keywords: lenmay
Platform: UNKNOWN
Classifier: Intended Audience :: Developers
Classifier: Natural Language :: English
Classifier: Programming Language :: Python :: 3.7
Requires-Dist: certifi (==2020.12.5)
Requires-Dist: chardet (==4.0.0)
Requires-Dist: click (==7.1.2)
Requires-Dist: idna (==2.10)
Requires-Dist: Jinja2 (==2.11.3)
Requires-Dist: MarkupSafe (==1.1.1)
Requires-Dist: requests (==2.25.1)
Requires-Dist: urllib3 (==1.26.3)
Requires-Dist: psutil (==5.8.0)
